upt_rubygems/__init__.py
upt_rubygems/upt_rubygems.py
upt_rubygems/tests/__init__.py
upt_rubygems/tests/test_upt_rubygems.py
upt_rubygems-0.4.1.dist-info/LICENSE
upt_rubygems-0.4.1.dist-info/METADATA
upt_rubygems-0.4.1.dist-info/WHEEL
upt_rubygems-0.4.1.dist-info/entry_points.txt
upt_rubygems-0.4.1.dist-info/top_level.txt
upt_rubygems-0.4.1.dist-info/RECORD
