Metadata-Version: 2.1
Name: upt-rubygems
Version: 0.4.1
Summary: RubyGems frontend for upt
Home-page: https://framagit.org/upt/upt-rubygems
Author: Cyril Roelandt
Author-email: tipecaml@gmail.com
License: UNKNOWN
Platform: UNKNOWN
Classifier: Development Status :: 3 - Alpha
Classifier: License :: OSI Approved :: BSD License
Classifier: Programming Language :: Python :: 3
Classifier: Programming Language :: Python :: 3.6
Classifier: Programming Language :: Python :: 3.7
Classifier: Programming Language :: Python :: 3.7
Requires-Dist: requests
Requires-Dist: semver
Requires-Dist: upt (>=0.11)
Provides-Extra: test
Requires-Dist: requests-mock ; extra == 'test'
